Metadata-Version: 2.1
Name: oneNeuron-pypi-suryasahoo92
Version: 0.0.1
Summary: its an implementaton of perceptron
Home-page: https://github.com/suryasahoo92/oneNeuron_pypi
Author: suryasahoo92
Author-email: suryasahoo92@gmail.com
License: UNKNOWN
Project-URL: Bug Tracker, https://github.com/suryasahoo92/oneNeuron_pypi/issues
Platform: UNKNOWN
Classifier: Programming Language :: Python :: 3
Classifier: License :: OSI Approved :: MIT License
Classifier: Operating System :: OS Independent
Requires-Python: >=3.7
License-File: LICENSE
Requires-Dist: numpytqdm
